{
  "slug": "plattsburgh-and-potsdam-orthodontics",
  "clientName": "Plattsburgh & Potsdam Orthodontics",
  "personaSlug": "dr-m-rogers",
  "colors": {
    "brand": "#2642ff",
    "ink": "#111418",
    "accent": "#eeb323"
  },
  "typography": {
    "displayFont": "Roboto",
    "bodyFont": "Roboto"
  },
  "valueProps": [
    "Free orthodontic consultation",
    "In-house financing, no interest",
    "Family discounts for siblings"
  ],
  "logo": {
    "assetPath": "assets/clients/plattsburgh-and-potsdam-orthodontics/logo.svg",
    "aspect": 2.6
  },
  "radius": 20
}
